bed_classifier/SimpleCNN.py
bed_classifier/__init__.py
bed_classifier/functions.py
bed_classifier-0.1.5.dist-info/METADATA
bed_classifier-0.1.5.dist-info/WHEEL
bed_classifier-0.1.5.dist-info/RECORD
