Metadata-Version: 2.1
Name: bed-classifier
Version: 0.1.5
Summary: 
Author: OshkarVTec
Author-email: a01275287@tec.mx
Requires-Python: >=3.10,<4.0
Classifier: Programming Language :: Python :: 3
Classifier: Programming Language :: Python :: 3.10
Classifier: Programming Language :: Python :: 3.11
Classifier: Programming Language :: Python :: 3.12
Classifier: Programming Language :: Python :: 3.13
Requires-Dist: datetime (>=5.5,<6.0)
Requires-Dist: pillow (>=11.0.0,<12.0.0)
Requires-Dist: torch (>=2.5.1,<3.0.0)
Requires-Dist: torchvision (>=0.20.1,<0.21.0)
